{  
   "name":"Response Shifting",
   "author":"University of Zurich (von Bastian & Druey)",
   "label":"response",
   "export":[  
      {  
         "mode":"upload",
         "auto":true,
         "enabled":true,
         "$$hashKey":"object:25989"
      },
      {  
         "mode":"download",
         "enabled":true,
         "$$hashKey":"object:25694"
      }
   ],
   "allowEscapeKey":true,
   "fullscreen":true,
   "moduleHierarchy":{  
      "tatoolType":"List",
      "label":"Task List",
      "iterator":{  
         "customType":"ListIterator",
         "numIterations":1
      },
      "children":[  
         {  
            "tatoolType":"Executable",
            "customType":"tatoolInstruction",
            "name":"instruction_response_01_practice",
            "blankInterval":0,
            "fixationInterval":0,
            "project":{  
               "name":"tatool",
               "access":"public"
            },
            "pages":{  
               "propertyType":"ArrayResource",
               "propertyValue":[  
                  {  
                     "project":{  
                        "name":"uzh-shifting-battery",
                        "access":"public"
                     },
                     "resourceName":"de_response_01_01.htm",
                     "resourceType":"instructions"
                  },
                  {  
                     "project":{  
                        "name":"uzh-shifting-battery",
                        "access":"public"
                     },
                     "resourceType":"instructions",
                     "resourceName":"de_response_01_02.htm"
                  },
                  {  
                     "project":{  
                        "name":"uzh-shifting-battery",
                        "access":"public"
                     },
                     "resourceType":"instructions",
                     "resourceName":"de_response_01_03.htm"
                  },
                  {  
                     "project":{  
                        "name":"uzh-shifting-battery",
                        "access":"public"
                     },
                     "resourceType":"instructions",
                     "resourceName":"de_response_01_04.htm"
                  }
               ]
            }
         },
         {  
            "tatoolType":"List",
            "name":"hftwdrabiuhy3mvi",
            "iterator":{  
               "customType":"ListIterator",
               "numIterations":24
            },
            "handlers":[  

            ],
            "children":[  
               {  
                  "tatoolType":"Executable",
                  "customType":"uzhShifting",
                  "name":"response_01_practice",
                  "blankInterval":"500",
                  "fixationInterval":0,
                  "project":{  
                     "name":"uzh-shifting-battery",
                     "access":"public"
                  },
                  "status":{  
                     "feedbackPanel":true
                  },
                  "stimuliPath":{  
                     "propertyType":"Path",
                     "project":{  
                        "name":"uzh-shifting-battery",
                        "access":"public"
                     },
                     "resourceName":"",
                     "resourceType":"stimuli"
                  },
                  "stimuliFile":{  
                     "propertyType":"Resource",
                     "project":{  
                        "name":"uzh-shifting-battery",
                        "access":"public"
                     },
                     "resourceName":"de_shifting_response_01_practice.csv",
                     "resourceType":"stimuli"
                  },
                  "displayCueDuration":"150"
               }
            ],
            "label":"practice_01"
         },
         {  
            "tatoolType":"Executable",
            "customType":"tatoolInstruction",
            "name":"instruction_endOfTask",
            "blankInterval":0,
            "fixationInterval":0,
            "project":{  
               "name":"tatool",
               "access":"public"
            },
            "pages":{  
               "propertyType":"ArrayResource",
               "propertyValue":[  
                  {  
                     "project":{  
                        "name":"uzh-shifting-battery",
                        "access":"public"
                     },
                     "resourceName":"de_general_00_endOfTask.htm",
                     "resourceType":"instructions"
                  }
               ]
            }
         },
         {  
            "tatoolType":"Executable",
            "customType":"tatoolInstruction",
            "name":"instruction_response_01_test",
            "blankInterval":0,
            "fixationInterval":0,
            "project":{  
               "name":"tatool",
               "access":"public"
            },
            "pages":{  
               "propertyType":"ArrayResource",
               "propertyValue":[  
                  {  
                     "project":{  
                        "name":"uzh-shifting-battery",
                        "access":"public"
                     },
                     "resourceName":"de_response_01_05.htm",
                     "resourceType":"instructions"
                  }
               ]
            }
         },
         {  
            "tatoolType":"List",
            "name":"phr4za9lidkrm0ia",
            "iterator":{  
               "customType":"ListIterator",
               "numIterations":145
            },
            "handlers":[  

            ],
            "children":[  
               {  
                  "tatoolType":"Executable",
                  "customType":"uzhShifting",
                  "name":"response_01",
                  "blankInterval":"500",
                  "fixationInterval":0,
                  "project":{  
                     "name":"uzh-shifting-battery",
                     "access":"public"
                  },
                  "stimuliPath":{  
                     "propertyType":"Path",
                     "project":{  
                        "name":"uzh-shifting-battery",
                        "access":"public"
                     },
                     "resourceName":"",
                     "resourceType":"stimuli"
                  },
                  "stimuliFile":{  
                     "propertyType":"Resource",
                     "project":{  
                        "name":"uzh-shifting-battery",
                        "access":"public"
                     },
                     "resourceName":"de_shifting_response_01.csv",
                     "resourceType":"stimuli"
                  },
                  "displayCueDuration":"150"
               }
            ],
            "label":"test_01"
         },
         {  
            "tatoolType":"Executable",
            "customType":"tatoolInstruction",
            "name":"instruction_endOfTask",
            "blankInterval":0,
            "fixationInterval":0,
            "project":{  
               "name":"tatool",
               "access":"public"
            }
         },
         {  
            "tatoolType":"Executable",
            "customType":"tatoolInstruction",
            "name":"instruction_response_02_practice",
            "blankInterval":0,
            "fixationInterval":0,
            "project":{  
               "name":"tatool",
               "access":"public"
            },
            "pages":{  
               "propertyType":"ArrayResource",
               "propertyValue":[  
                  {  
                     "project":{  
                        "name":"uzh-shifting-battery",
                        "access":"public"
                     },
                     "resourceName":"de_response_02_01.htm",
                     "resourceType":"instructions"
                  },
                  {  
                     "project":{  
                        "name":"uzh-shifting-battery",
                        "access":"public"
                     },
                     "resourceType":"instructions",
                     "resourceName":"de_response_02_02.htm"
                  },
                  {  
                     "project":{  
                        "name":"uzh-shifting-battery",
                        "access":"public"
                     },
                     "resourceType":"instructions",
                     "resourceName":"de_response_02_03.htm"
                  },
                  {  
                     "project":{  
                        "name":"uzh-shifting-battery",
                        "access":"public"
                     },
                     "resourceType":"instructions",
                     "resourceName":"de_response_02_04.htm"
                  }
               ]
            }
         },
         {  
            "tatoolType":"List",
            "name":"zopxtcqzygk9faet",
            "iterator":{  
               "customType":"ListIterator",
               "numIterations":24
            },
            "handlers":[  

            ],
            "children":[  
               {  
                  "tatoolType":"Executable",
                  "customType":"uzhShifting",
                  "name":"response_02_practice",
                  "blankInterval":0,
                  "fixationInterval":0,
                  "project":{  
                     "name":"uzh-shifting-battery",
                     "access":"public"
                  },
                  "stimuliPath":{  
                     "propertyType":"Path",
                     "project":{  
                        "name":"uzh-shifting-battery",
                        "access":"public"
                     },
                     "resourceName":"",
                     "resourceType":"stimuli"
                  },
                  "stimuliFile":{  
                     "propertyType":"Resource",
                     "project":{  
                        "name":"uzh-shifting-battery",
                        "access":"public"
                     },
                     "resourceName":"de_shifting_response_02_practice.csv",
                     "resourceType":"stimuli"
                  },
                  "displayCueDuration":"150"
               }
            ],
            "label":"practice_02"
         },
         {  
            "tatoolType":"Executable",
            "customType":"tatoolInstruction",
            "name":"instruction_endOfTask",
            "blankInterval":0,
            "fixationInterval":0,
            "project":{  
               "name":"tatool",
               "access":"public"
            }
         },
         {  
            "tatoolType":"Executable",
            "customType":"tatoolInstruction",
            "name":"instruction_response_02_test",
            "blankInterval":0,
            "fixationInterval":0,
            "project":{  
               "name":"tatool",
               "access":"public"
            },
            "pages":{  
               "propertyType":"ArrayResource",
               "propertyValue":[  
                  {  
                     "project":{  
                        "name":"uzh-shifting-battery",
                        "access":"public"
                     },
                     "resourceName":"de_response_02_05.htm",
                     "resourceType":"instructions"
                  }
               ]
            }
         },
         {  
            "tatoolType":"List",
            "name":"faj1z48umywbemq6",
            "iterator":{  
               "customType":"ListIterator",
               "numIterations":145
            },
            "handlers":[  

            ],
            "children":[  
               {  
                  "tatoolType":"Executable",
                  "customType":"uzhShifting",
                  "name":"response_02",
                  "blankInterval":"500",
                  "fixationInterval":0,
                  "project":{  
                     "name":"uzh-shifting-battery",
                     "access":"public"
                  },
                  "stimuliPath":{  
                     "propertyType":"Path",
                     "project":{  
                        "name":"uzh-shifting-battery",
                        "access":"public"
                     },
                     "resourceName":"",
                     "resourceType":"stimuli"
                  },
                  "stimuliFile":{  
                     "propertyType":"Resource",
                     "project":{  
                        "name":"uzh-shifting-battery",
                        "access":"public"
                     },
                     "resourceName":"de_shifting_response_02.csv",
                     "resourceType":"stimuli"
                  },
                  "displayCueDuration":"150"
               }
            ],
            "label":"test_02"
         },
         {  
            "tatoolType":"Executable",
            "customType":"tatoolInstruction",
            "name":"instruction_endOfTask",
            "blankInterval":0,
            "fixationInterval":0,
            "project":{  
               "name":"tatool",
               "access":"public"
            }
         },
         {  
            "tatoolType":"Executable",
            "customType":"tatoolInstruction",
            "name":"instruction_response_03_practice",
            "blankInterval":0,
            "fixationInterval":0,
            "project":{  
               "name":"tatool",
               "access":"public"
            },
            "pages":{  
               "propertyType":"ArrayResource",
               "propertyValue":[  
                  {  
                     "project":{  
                        "name":"uzh-shifting-battery",
                        "access":"public"
                     },
                     "resourceName":"de_response_03_01.htm",
                     "resourceType":"instructions"
                  },
                  {  
                     "project":{  
                        "name":"uzh-shifting-battery",
                        "access":"public"
                     },
                     "resourceType":"instructions",
                     "resourceName":"de_response_03_02.htm"
                  },
                  {  
                     "project":{  
                        "name":"uzh-shifting-battery",
                        "access":"public"
                     },
                     "resourceType":"instructions",
                     "resourceName":"de_response_03_03.htm"
                  },
                  {  
                     "project":{  
                        "name":"uzh-shifting-battery",
                        "access":"public"
                     },
                     "resourceType":"instructions",
                     "resourceName":"de_response_03_04.htm"
                  }
               ]
            }
         },
         {  
            "tatoolType":"List",
            "name":"d8o7jnyhtt99pmnt",
            "iterator":{  
               "customType":"ListIterator",
               "numIterations":24
            },
            "handlers":[  

            ],
            "children":[  
               {  
                  "tatoolType":"Executable",
                  "customType":"uzhShifting",
                  "name":"response_03_practice",
                  "blankInterval":0,
                  "fixationInterval":0,
                  "project":{  
                     "name":"uzh-shifting-battery",
                     "access":"public"
                  },
                  "stimuliPath":{  
                     "propertyType":"Path",
                     "project":{  
                        "name":"uzh-shifting-battery",
                        "access":"public"
                     },
                     "resourceName":"",
                     "resourceType":"stimuli"
                  },
                  "stimuliFile":{  
                     "propertyType":"Resource",
                     "project":{  
                        "name":"uzh-shifting-battery",
                        "access":"public"
                     },
                     "resourceName":"de_shifting_response_03_practice.csv",
                     "resourceType":"stimuli"
                  },
                  "displayCueDuration":"150"
               }
            ],
            "label":"practice_03"
         },
         {  
            "tatoolType":"Executable",
            "customType":"tatoolInstruction",
            "name":"instruction_endOfTask",
            "blankInterval":0,
            "fixationInterval":0,
            "project":{  
               "name":"tatool",
               "access":"public"
            }
         },
         {  
            "tatoolType":"Executable",
            "customType":"tatoolInstruction",
            "name":"instruction_response_03_test",
            "blankInterval":0,
            "fixationInterval":0,
            "project":{  
               "name":"tatool",
               "access":"public"
            },
            "pages":{  
               "propertyType":"ArrayResource",
               "propertyValue":[  
                  {  
                     "project":{  
                        "name":"uzh-shifting-battery",
                        "access":"public"
                     },
                     "resourceName":"de_response_03_05.htm",
                     "resourceType":"instructions"
                  }
               ]
            }
         },
         {  
            "tatoolType":"List",
            "name":"q2ws9vwtdx17rvwf",
            "iterator":{  
               "customType":"ListIterator",
               "numIterations":145
            },
            "handlers":[  

            ],
            "children":[  
               {  
                  "tatoolType":"Executable",
                  "customType":"uzhShifting",
                  "name":"response_03",
                  "blankInterval":"500",
                  "fixationInterval":0,
                  "project":{  
                     "name":"uzh-shifting-battery",
                     "access":"public"
                  },
                  "stimuliPath":{  
                     "propertyType":"Path",
                     "project":{  
                        "name":"uzh-shifting-battery",
                        "access":"public"
                     },
                     "resourceName":"",
                     "resourceType":"stimuli"
                  },
                  "stimuliFile":{  
                     "propertyType":"Resource",
                     "project":{  
                        "name":"uzh-shifting-battery",
                        "access":"public"
                     },
                     "resourceName":"de_shifting_response_03.csv",
                     "resourceType":"stimuli"
                  },
                  "displayCueDuration":"150"
               }
            ],
            "label":"test_03"
         },
         {  
            "tatoolType":"Executable",
            "customType":"tatoolInstruction",
            "name":"instruction_endOfTask",
            "blankInterval":0,
            "fixationInterval":0,
            "project":{  
               "name":"tatool",
               "access":"public"
            }
         },
         {  
            "tatoolType":"Executable",
            "customType":"tatoolInstruction",
            "name":"instruction_response_04_practice",
            "blankInterval":0,
            "fixationInterval":0,
            "project":{  
               "name":"tatool",
               "access":"public"
            },
            "pages":{  
               "propertyType":"ArrayResource",
               "propertyValue":[  
                  {  
                     "project":{  
                        "name":"uzh-shifting-battery",
                        "access":"public"
                     },
                     "resourceName":"de_response_04_01.htm",
                     "resourceType":"instructions"
                  },
                  {  
                     "project":{  
                        "name":"uzh-shifting-battery",
                        "access":"public"
                     },
                     "resourceType":"instructions",
                     "resourceName":"de_response_04_02.htm"
                  },
                  {  
                     "project":{  
                        "name":"uzh-shifting-battery",
                        "access":"public"
                     },
                     "resourceType":"instructions",
                     "resourceName":"de_response_04_03.htm"
                  },
                  {  
                     "project":{  
                        "name":"uzh-shifting-battery",
                        "access":"public"
                     },
                     "resourceType":"instructions",
                     "resourceName":"de_response_04_04.htm"
                  }
               ]
            }
         },
         {  
            "tatoolType":"List",
            "name":"qlk3m5z3tz5mjb1s",
            "iterator":{  
               "customType":"ListIterator",
               "numIterations":24
            },
            "handlers":[  

            ],
            "children":[  
               {  
                  "tatoolType":"Executable",
                  "customType":"uzhShifting",
                  "name":"response_04_practice",
                  "blankInterval":"500",
                  "fixationInterval":0,
                  "project":{  
                     "name":"uzh-shifting-battery",
                     "access":"public"
                  },
                  "stimuliPath":{  
                     "propertyType":"Path",
                     "project":{  
                        "name":"uzh-shifting-battery",
                        "access":"public"
                     },
                     "resourceName":"",
                     "resourceType":"stimuli"
                  },
                  "stimuliFile":{  
                     "propertyType":"Resource",
                     "project":{  
                        "name":"uzh-shifting-battery",
                        "access":"public"
                     },
                     "resourceName":"de_shifting_response_04_practice.csv",
                     "resourceType":"stimuli"
                  },
                  "displayCueDuration":"150"
               }
            ],
            "label":"practice_04"
         },
         {  
            "tatoolType":"Executable",
            "customType":"tatoolInstruction",
            "name":"instruction_endOfTask",
            "blankInterval":0,
            "fixationInterval":0,
            "project":{  
               "name":"tatool",
               "access":"public"
            }
         },
         {  
            "tatoolType":"Executable",
            "customType":"tatoolInstruction",
            "name":"instruction_response_04_test",
            "blankInterval":0,
            "fixationInterval":0,
            "project":{  
               "name":"tatool",
               "access":"public"
            },
            "pages":{  
               "propertyType":"ArrayResource",
               "propertyValue":[  
                  {  
                     "project":{  
                        "name":"uzh-shifting-battery",
                        "access":"public"
                     },
                     "resourceName":"de_response_04_05.htm",
                     "resourceType":"instructions"
                  }
               ]
            },
            "images":{  
               "propertyType":"ArrayResource",
               "propertyValue":[  

               ]
            }
         },
         {  
            "tatoolType":"List",
            "name":"g87pda2ch8unsp2d",
            "iterator":{  
               "customType":"ListIterator",
               "numIterations":145
            },
            "handlers":[  

            ],
            "children":[  
               {  
                  "tatoolType":"Executable",
                  "customType":"uzhShifting",
                  "name":"response_04",
                  "blankInterval":"500",
                  "fixationInterval":0,
                  "project":{  
                     "name":"uzh-shifting-battery",
                     "access":"public"
                  },
                  "stimuliPath":{  
                     "propertyType":"Path",
                     "project":{  
                        "name":"uzh-shifting-battery",
                        "access":"public"
                     },
                     "resourceName":"",
                     "resourceType":"stimuli"
                  },
                  "stimuliFile":{  
                     "propertyType":"Resource",
                     "project":{  
                        "name":"uzh-shifting-battery",
                        "access":"public"
                     },
                     "resourceName":"de_shifting_response_04.csv",
                     "resourceType":"stimuli"
                  },
                  "displayCueDuration":"150"
               }
            ],
            "label":"test_04"
         },
         {  
            "tatoolType":"Executable",
            "customType":"tatoolInstruction",
            "name":"instruction_endOfBlock",
            "blankInterval":0,
            "fixationInterval":0,
            "project":{  
               "name":"tatool",
               "access":"public"
            },
            "pages":{  
               "propertyType":"ArrayResource",
               "propertyValue":[  
                  {  
                     "project":{  
                        "name":"uzh-shifting-battery",
                        "access":"public"
                     },
                     "resourceName":"de_general_08_endOfBlock.htm",
                     "resourceType":"instructions"
                  }
               ]
            }
         }
      ]
   },
   "description":"Response Shifting tasks from von Bastian, C. C. & Druey, M. D. (submitted). Shifting between mental sets: An individual differences approach to commonalities and differences of task switching components. Journal of Experimental Psychology: General. doi: 10.1037/xge0000333"
}